rate_limit_guard/__init__.py
rate_limit_guard/decorator.py
rate_limit_guard/guard.py
rate_limit_guard-0.1.3.dist-info/METADATA
rate_limit_guard-0.1.3.dist-info/WHEEL
rate_limit_guard-0.1.3.dist-info/RECORD
