Metadata-Version: 2.1
Name: rate-limit-guard
Version: 0.1.3
Summary: 
Home-page: https://github.com/izofat/rate-limit-guard
License: MIT
Keywords: rate limiter,API,decorator
Author: Gorkem Kacar
Author-email: g.kacar@digitastic.app
Requires-Python: >=3.11,<4.0
Classifier: License :: OSI Approved :: MIT License
Classifier: Programming Language :: Python :: 3
Classifier: Programming Language :: Python :: 3.11
Classifier: Programming Language :: Python :: 3.12
Classifier: Programming Language :: Python :: 3.13
Requires-Dist: asyncio (>=3.4.3,<4.0.0)
Project-URL: Repository, https://github.com/izofat/rate-limit-guard
